mutation_load/__init__.py
mutation_load/mutation_load.py
mutation_load/r_scripts/mutation_load_coverages_multiple_files.R
mutation_load/r_scripts/mutation_load_coverages_onefile.R
mutation_load/regex_patterns/__init__.py
mutation_load/regex_patterns/regex_patterns.py
mutation_load/resources/mutation_load_config.ini
mutation_load-1.0.4111115.dist-info/LICENSE
mutation_load-1.0.4111115.dist-info/METADATA
mutation_load-1.0.4111115.dist-info/WHEEL
mutation_load-1.0.4111115.dist-info/entry_points.txt
mutation_load-1.0.4111115.dist-info/top_level.txt
mutation_load-1.0.4111115.dist-info/RECORD
