Metadata-Version: 2.1
Name: mutation_load
Version: 1.0.4111115
Summary: VCF permutation tool
Home-page: https://github.com/jarvint12/mutation_load
Author: Timo_Järvinen
Author-email: neville160@gmail.com
License: UNKNOWN
Platform: UNKNOWN
Classifier: Programming Language :: Python
Classifier: Programming Language :: Python :: 3
Classifier: License :: OSI Approved :: BSD License
Classifier: Operating System :: POSIX :: Linux
Classifier: Intended Audience :: Science/Research
Classifier: Topic :: Scientific/Engineering
Classifier: Topic :: Scientific/Engineering :: Bio-Informatics
License-File: LICENSE
